binfilepy/__init__.py
binfilepy/binfile.py
binfilepy/constant.py
tests/__init__.py
tests/test_binfilepy.py
binfilepy-0.1.2.dist-info/LICENSE
binfilepy-0.1.2.dist-info/METADATA
binfilepy-0.1.2.dist-info/WHEEL
binfilepy-0.1.2.dist-info/top_level.txt
binfilepy-0.1.2.dist-info/RECORD
