Metadata-Version: 2.1
Name: binfilepy
Version: 0.1.2
Summary: Package for read/write binary file (.adibin format)
Home-page: https://github.com/hulab-ucsf/binfilepy.git
Author: Peter Li@HuLab UCSF
Author-email: peter0306@gmail.com
License: UNKNOWN
Keywords: ECG EKG binary chart adibin
Platform: UNKNOWN
Classifier: Programming Language :: Python :: 3
Classifier: License :: OSI Approved :: MIT License
Classifier: Operating System :: OS Independent
Requires-Python: >=2.7, !=3.0.*, !=3.1.*, !=3.2.*, !=3.3.*, <4
